opttrot_tp-0.0.3.dist-info/licenses/License
tp/__init__.py
tp/tp.py
tp/utils.py
opttrot_tp-0.0.3.dist-info/METADATA
opttrot_tp-0.0.3.dist-info/WHEEL
opttrot_tp-0.0.3.dist-info/top_level.txt
opttrot_tp-0.0.3.dist-info/RECORD
