Metadata-Version: 2.4
Name: opttrot-tp
Version: 0.0.3
Summary: A simple Hamiltonian matrix decompose and compose routines based on tensorized method.
Author-email: Hyunseong Kim <Hyunseong.Kim@rice.edu>
License-Expression: MIT
Project-URL: Homepage, https://github.com/OptTrot/Tensorized-Pauli-Composer
Project-URL: Issues, https://github.com/OptTrot/Tensorized-Pauli-Composer/issues
Keywords: Pauli,Matrix,Hamiltonian,Decomposition,Composition
Classifier: Programming Language :: Python :: 3
Classifier: Operating System :: OS Independent
Requires-Python: >=3.7
License-File: License
Requires-Dist: numpy>=1.20.0
Requires-Dist: scipy
Dynamic: license-file
